qfex/__init__.py
qfex/client.py
qfex/config.py
qfex/models.py
qfex/strategy.py
qfex-0.1.0.dist-info/METADATA
qfex-0.1.0.dist-info/WHEEL
qfex-0.1.0.dist-info/top_level.txt
qfex-0.1.0.dist-info/RECORD
