Metadata-Version: 2.4
Name: qfex
Version: 0.1.0
Summary: A Python SDK for the QFEX Taker API
Author-email: QFEX <support@qfex.com>
License: MIT
Project-URL: Homepage, https://github.com/qfex-org/qfex-py
Classifier: Programming Language :: Python :: 3
Classifier: License :: OSI Approved :: MIT License
Classifier: Operating System :: OS Independent
Requires-Python: >=3.7
Requires-Dist: websockets>=10.0
